LICENSE
MANIFEST.in
README.md
setup.py
mandrill_inbound/__init__.py
python_mandrill_inbound.egg-info/PKG-INFO
python_mandrill_inbound.egg-info/SOURCES.txt
python_mandrill_inbound.egg-info/dependency_links.txt
python_mandrill_inbound.egg-info/top_level.txt