Metadata-Version: 1.1
Name: python-mandrill-inbound
Version: 0.0.2
Summary: Python wrapper for Mandrill Inbound
Home-page: https://github.com/jpadilla/mandrill-inbound-python
Author: José Padilla
Author-email: jpadilla@webapplicate.com
License: MIT License
Download-URL: https://github.com/jpadilla/mandrill-inbound-python/tarball/master
Platform: UNKNOWN
